codestare/compiletools/__init__.py
codestare/compiletools/cmd.py
codestare/compiletools/compile.py
codestare/compiletools/init_template
codestare/compiletools/options.py
codestare_msg_compiler-0.0.6.dist-info/LICENSE.rst
codestare_msg_compiler-0.0.6.dist-info/METADATA
codestare_msg_compiler-0.0.6.dist-info/WHEEL
codestare_msg_compiler-0.0.6.dist-info/entry_points.txt
codestare_msg_compiler-0.0.6.dist-info/top_level.txt
codestare_msg_compiler-0.0.6.dist-info/RECORD
