Metadata-Version: 2.1
Name: codestare-msg-compiler
Version: 0.0.6
Summary: "Distutils / Setuptools package to automatically compile and process protobuf files."
Home-page: https://github.com/saggitar/codestare-msg-compiler.git
Author: Maximilian Schmidt
Author-email: ga97lul@mytum.de
Keywords: protobuf,proto-plus
Classifier: Programming Language :: Python :: 3
Requires-Python: >=3.7
License-File: LICENSE.rst
Provides-Extra: betterproto
Requires-Dist: betterproto[compiler] ; extra == 'betterproto'
Provides-Extra: cli
Requires-Dist: fire ; extra == 'cli'
Provides-Extra: docs
Requires-Dist: sphinx (==4.2.0) ; extra == 'docs'
Requires-Dist: importlib-metadata ; (python_version < "3.8") and extra == 'docs'
Provides-Extra: mypy
Requires-Dist: mypy ; extra == 'mypy'
Requires-Dist: mypy-protobuf ; extra == 'mypy'
Provides-Extra: protoplus
Requires-Dist: codestare-proto-plus (>=0.0.5) ; extra == 'protoplus'
